MANIFEST.in
setup.cfg
setup.py
crm/__init__.py
crm/devsettings.py
crm/settings.py
crm/urls.py
crm/wsgi.py
crm/admin/__init__.py
crm/admin/dashboard.py
crm/admin/tests.py
crm/contract/__init__.py
crm/contract/tests.py
crm/contract/urls.py
crm/contract/views.py
crm/contract/admin/__init__.py
crm/contract/admin/addendum.py
crm/contract/admin/contract.py
crm/contract/admin/document.py
crm/contract/admin/ticket.py
crm/contract/migrations/__init__.py
crm/contract/models/__init__.py
crm/contract/models/addendum.py
crm/contract/models/contract.py
crm/contract/models/document.py
crm/contract/models/ticket.py
crm/customer/__init__.py
crm/customer/tests.py
crm/customer/admin/__init__.py
crm/customer/admin/city.py
crm/customer/admin/country.py
crm/customer/admin/customer.py
crm/customer/admin/document.py
crm/customer/admin/state.py
crm/customer/admin/zipcode.py
crm/customer/migrations/__init__.py
crm/customer/models/__init__.py
crm/customer/models/city.py
crm/customer/models/country.py
crm/customer/models/customer.py
crm/customer/models/document.py
crm/customer/models/state.py
crm/customer/models/zipcode.py
crm/date/__init__.py
crm/date/admin.py
crm/date/models.py
crm/date/tests.py
crm/date/migrations/__init__.py
crm/date/templatetags/__init__.py
crm/date/templatetags/events.py
crm/date/templatetags/month.py
crm/group/__init__.py
crm/group/tests.py
crm/group/urls.py
crm/group/admin/__init__.py
crm/group/admin/category.py
crm/group/admin/entry.py
crm/group/admin/group.py
crm/group/admin/instructor.py
crm/group/admin/level.py
crm/group/admin/pool.py
crm/group/admin/type.py
crm/group/admin/variant.py
crm/group/migrations/__init__.py
crm/group/models/__init__.py
crm/group/models/category.py
crm/group/models/entry.py
crm/group/models/group.py
crm/group/models/instructor.py
crm/group/models/level.py
crm/group/models/pool.py
crm/group/models/type.py
crm/group/models/variant.py
crm/group/views/__init__.py
crm/group/views/group.py
crm/group/views/json.py
crm/payment/__init__.py
django_spa_crm.egg-info/PKG-INFO
django_spa_crm.egg-info/SOURCES.txt
django_spa_crm.egg-info/dependency_links.txt
django_spa_crm.egg-info/not-zip-safe
django_spa_crm.egg-info/requires.txt
django_spa_crm.egg-info/top_level.txt