Metadata-Version: 1.1
Name: django-spa-crm
Version: 1.0.0
Summary: Django SPA CRM
Home-page: http://mattagile.com/
Author: Matt Harasymczuk
Author-email: code@mattagile.com
License: Apache License 2.0
Download-URL: https://github.com/MattAgile/django-spa-crm
Platform: UNKNOWN
Classifier: Development Status :: 5 - Production/Stable
Classifier: Framework :: Django
Classifier: Intended Audience :: Healthcare Industry
Classifier: Intended Audience :: Other Audience
Classifier: License :: OSI Approved :: Apache Software License
Classifier: Natural Language :: English
Classifier: Natural Language :: Polish
Classifier: Operating System :: OS Independent
Classifier: Programming Language :: JavaScript
Classifier: Programming Language :: Python :: 3.4
Classifier: Topic :: Internet :: WWW/HTTP :: WSGI :: Application
